SoftwareHelper/__init__.py
SoftwareHelper/log.py
SoftwareHelper/main.py
SoftwareHelper-0.0.1.dist-info/DESCRIPTION.rst
SoftwareHelper-0.0.1.dist-info/METADATA
SoftwareHelper-0.0.1.dist-info/RECORD
SoftwareHelper-0.0.1.dist-info/WHEEL
SoftwareHelper-0.0.1.dist-info/entry_points.txt
SoftwareHelper-0.0.1.dist-info/metadata.json
SoftwareHelper-0.0.1.dist-info/top_level.txt
