Metadata-Version: 2.0
Name: SoftwareHelper
Version: 0.0.1
Summary: Project generator for software creating by the Python programming language
Home-page: https://github.com/setivolkylany/SoftwareHelper
Author: setivolkylany
Author-email: setivolkylany@gmail.com
License: BSD
Keywords: Python,project-generator,skeleton,structure,package,application,packaging
Platform: UNKNOWN
Classifier: Development Status :: 1 - Planning
Classifier: Intended Audience :: Developers
Classifier: Topic :: Software Development
Classifier: License :: OSI Approved :: BSD License
Classifier: Natural Language :: English
Classifier: Programming Language :: Python :: 3.4
Classifier: Programming Language :: Python :: 3.5
Classifier: Programming Language :: Python :: Implementation :: CPython
Requires-Dist: invoke (==0.13.0)
Provides-Extra: dev
Provides-Extra: test
